README.md
setup.py
jarvis/__init__.py
jarvis/__main__.py
jarvis/constants.py
jarvis/utils.py
jarvis_cmd.egg-info/PKG-INFO
jarvis_cmd.egg-info/SOURCES.txt
jarvis_cmd.egg-info/dependency_links.txt
jarvis_cmd.egg-info/entry_points.txt
jarvis_cmd.egg-info/requires.txt
jarvis_cmd.egg-info/top_level.txt